MANIFEST.in
README.md
pyproject.toml
requirements.in
setup.py
notabene/__init__.py
notabene/base.py
notabene/cli.py
notabene/template.py
notabene/utils.py
notabene/version.py
notabene_cli.egg-info/PKG-INFO
notabene_cli.egg-info/SOURCES.txt
notabene_cli.egg-info/dependency_links.txt
notabene_cli.egg-info/entry_points.txt
notabene_cli.egg-info/requires.txt
notabene_cli.egg-info/top_level.txt