Metadata-Version: 2.1
Name: notabene-cli
Version: 0.0.5
Summary: The command line interface for interacting with notabene.
Home-page: https://github.com/JeroenPeterBos/notabene
Author: Jeroen Peter Bos
Author-email: jeroen@notabene.cloud
License: UNKNOWN
Project-URL: Homepage, https://notabene.cloud/
Project-URL: Source Code, https://github.com/JeroenPeterBos/notabene
Project-URL: Documentation, https://notabene-cli.readthedocs.io/
Platform: UNKNOWN
Classifier: Development Status :: 3 - Alpha
Classifier: Intended Audience :: Developers
Classifier: Intended Audience :: Science/Research
Classifier: Topic :: Software Development :: Libraries
Classifier: Programming Language :: Python :: 3.7
Classifier: Programming Language :: Python :: 3.8
Classifier: Programming Language :: Python :: 3.9
Classifier: Framework :: Jupyter
Requires-Python: >=3.6
